whiscy/__init__.py
whiscy/cli.py
whiscy/cli_bfactor.py
whiscy/cli_consadjust.py
whiscy/cli_haddock.py
whiscy/cli_parasmooth.py
whiscy/cli_resdist.py
whiscy/cli_setup.py
whiscy/modules/__init__.py
whiscy/modules/access.py
whiscy/modules/hssp.py
whiscy/modules/pam_calc.py
whiscy/modules/pam_data.py
whiscy/modules/pdbutil.py
whiscy/modules/quotes.py
whiscy/modules/whiscy_data.py
whiscy/param/parasmooth.par
whiscy/param/weight_ma.txt
whiscy/param/ztable.txt
whiscy-1.2.0.dist-info/LICENSE
whiscy-1.2.0.dist-info/METADATA
whiscy-1.2.0.dist-info/WHEEL
whiscy-1.2.0.dist-info/entry_points.txt
whiscy-1.2.0.dist-info/RECORD
