Metadata-Version: 2.1
Name: whiscy
Version: 1.2.0
Summary: WHISCY is a software that predicts protein-protein interfaces using conservation and structural information by calculating prediction scores for each surface residue based on sequence alignment.
Author: Bonvin Lab
Author-email: bonvinlab.support@uu.nl
Requires-Python: >=3.11,<4.0
Classifier: Development Status :: 5 - Production/Stable
Classifier: Intended Audience :: Science/Research
Classifier: License :: OSI Approved :: Apache Software License
Classifier: Operating System :: Unix
Classifier: Programming Language :: Python :: 3
Classifier: Programming Language :: Python :: 3.11
Classifier: Programming Language :: Python :: 3.12
Classifier: Topic :: Scientific/Engineering :: Bio-Informatics
Requires-Dist: biopython (==1.79)
